lineid_plot/__init__.py
lineid_plot/lineid_plot.py
lineid_plot/utils.py
lineid_plot/version.py
lineid_plot-0.6.dist-info/DESCRIPTION.rst
lineid_plot-0.6.dist-info/METADATA
lineid_plot-0.6.dist-info/RECORD
lineid_plot-0.6.dist-info/WHEEL
lineid_plot-0.6.dist-info/metadata.json
lineid_plot-0.6.dist-info/top_level.txt
