Metadata-Version: 2.0
Name: lineid-plot
Version: 0.6
Summary: Automatic placement of labels in a plot.
Home-page: https://github.com/phn/lineid_plot
Author: Prasanth Nair
Author-email: prasanthhn@gmail.com
License: BSD
Platform: UNKNOWN
Classifier: Development Status :: 6 - Mature
Classifier: Intended Audience :: Science/Research
Classifier: License :: OSI Approved :: BSD License
Classifier: Topic :: Scientific/Engineering :: Astronomy
Classifier: Topic :: Scientific/Engineering :: Physics
Classifier: Programming Language :: Python :: 2.7
Classifier: Programming Language :: Python :: 3
Classifier: Programming Language :: Python :: 3.5
Classifier: Programming Language :: Python :: 3.6
